Workbook

Sheet Product_clean
A1: Product ID | B1: Product Name | C1: Category | D1: Sub-Category | E1: Price | F1: Discount Price | G1: Ratings | H1: Reviews | I1: Seller Name | J1: Min_Delivery_Days | K1: Max_Delivery_days | L1: Cost_Price | M1: Discount_Amount | N1: Profit_Per_unit | O1: Profit_Margin_% | P1: Delivery Time | Q1: Availability
A2: MS001 | B2: Women's Rayon Printed Kurti | C2: Clothing | D2: Kurtis | E2: 699 | F2: 349 | G2: 4.2 | H2: 1250 | I2: TrendyHub | J2: =LEFT(P2,1) -> 5 | K2: =MID(P2,3,1) -> 7 | L2: =E2*0.65 -> 454.35 | M2: =E2-F2 -> 350 | N2: =F2 - L2 -> -105.35 | O2: =(N2/F2) -> -0.30186246 | P2: 5-7 Days | Q2: In-Stock
A3: MS002 | B3: Cotton Blend Saree | C3: Clothing | D3: Sarees | E3: 1199 | F3: 549 | G3: 4 | H3: 980 | I3: SareeVilla | J3: =LEFT(P3,1) -> 6 | K3: =MID(P3,3,1) -> 8 | L3: =E3*0.65 -> 779.35 | M3: =E3-F3 -> 650 | N3: =F3 - L3 -> -230.35 | O3: =(N3/F3) -> -0.41958106 | P3: 6-8 Days | Q3: In-Stock
A4: MS003 | B4: Men's Casual Slim Fit Shirt | C4: Men's Fashion | D4: Shirts | E4: 799 | F4: 399 | G4: 4.3 | H4: 650 | I4: UrbanWear | J4: =LEFT(P4,1) -> 4 | K4: =MID(P4,3,1) -> 6 | L4: =E4*0.65 -> 519.35 | M4: =E4-F4 -> 400 | N4: =F4 - L4 -> -120.35 | O4: =(N4/F4) -> -0.30162907 | P4: 4-6 Days | Q4: In-Stock
A5: MS004 | B5: Women's Ankle Length Leggings | C5: Clothing | D5: Bottomwear | E5: 299 | F5: 179 | G5: 4.1 | H5: 1150 | I5: LeggingsWorld | J5: =LEFT(P5,1) -> 5 | K5: =MID(P5,3,1) -> 7 | L5: =E5*0.65 -> 194.35 | M5: =E5-F5 -> 120 | N5: =F5 - L5 -> -15.35 | O5: =(N5/F5) -> -0.08575419 | P5: 5-7 Days | Q5: In-Stock
A6: MS005 | B6: Stainless Steel Water Bottle 1L | C6: Home | D6: Kitchen | E6: 499 | F6: 249 | G6: 4.5 | H6: 820 | I6: HomeEssentials | J6: =LEFT(P6,1) -> 3 | K6: =MID(P6,3,1) -> 5 | L6: =E6*0.65 -> 324.35 | M6: =E6-F6 -> 250 | N6: =F6 - L6 -> -75.35 | O6: =(N6/F6) -> -0.30261044 | P6: 3-5 Days | Q6: In-Stock
A7: MS006 | B7: Printed Bedsheet with Pillow Covers | C7: Home | D7: Bedding | E7: 899 | F7: 499 | G7: 4.2 | H7: 720 | I7: DecorMagic | J7: =LEFT(P7,1) -> 5 | K7: =MID(P7,3,1) -> 8 | L7: =E7*0.65 -> 584.35 | M7: =E7-F7 -> 400 | N7: =F7 - L7 -> -85.35 | O7: =(N7/F7) -> -0.17104208 | P7: 5-8 Days | Q7: In-Stock
A8: MS007 | B8: Soft Baby Cotton Romper | C8: Kids | D8: Babywear | E8: 499 | F8: 259 | G8: 4.6 | H8: 500 | I8: LittleStars | J8: =LEFT(P8,1) -> 4 | K8: =MID(P8,3,1) -> 6 | L8: =E8*0.65 -> 324.35 | M8: =E8-F8 -> 240 | N8: =F8 - L8 -> -65.35 | O8: =(N8/F8) -> -0.2523166 | P8: 4-6 Days | Q8: In-Stock
A9: MS008 | B9: Women's Faux Leather Handbag | C9: Accessories | D9: Bags | E9: 1299 | F9: 699 | G9: 4.3 | H9: 430 | I9: FashionBagHub | J9: =LEFT(P9,1) -> 5 | K9: =MID(P9,3,1) -> 7 | L9: =E9*0.65 -> 844.35 | M9: =E9-F9 -> 600 | N9: =F9 - L9 -> -145.35 | O9: =(N9/F9) -> -0.20793991 | P9: 5-7 Days | Q9: In-Stock
A10: MS009 | B10: Men's Running Sports Shoes | C10: Footwear | D10: Sports Shoes | E10: 1499 | F10: 799 | G10: 4.4 | H10: 780 | I10: Sportify | J10: =LEFT(P10,1) -> 4 | K10: =MID(P10,3,1) -> 6 | L10: =E10*0.65 -> 974.35 | M10: =E10-F10 -> 700 | N10: =F10 - L10 -> -175.35 | O10: =(N10/F10) -> -0.21946183 | P10: 4-6 Days | Q10: In-Stock
A11: MS010 | B11: Women's Oxidised Silver Earrings | C11: Jewellery | D11: Earrings | E11: 399 | F11: 189 | G11: 4.5 | H11: 1050 | I11: JewelWorld | J11: =LEFT(P11,1) -> 3 | K11: =MID(P11,3,1) -> 5 | L11: =E11*0.65 -> 259.35 | M11: =E11-F11 -> 210 | N11: =F11 - L11 -> -70.35 | O11: =(N11/F11) -> -0.37222222 | P11: 3-5 Days | Q11: In-Stock
A12: MS011 | B12: Microfiber Double Bedsheet | C12: Home | D12: Bedding | E12: 999 | F12: 499 | G12: 4.2 | H12: 620 | I12: ComfortZone | J12: =LEFT(P12,1) -> 5 | K12: =MID(P12,3,1) -> 7 | L12: =E12*0.65 -> 649.35 | M12: =E12-F12 -> 500 | N12: =F12 - L12 -> -150.35 | O12: =(N12/F12) -> -0.30130261 | P12: 5-7 Days | Q12: In-Stock
A13: MS012 | B13: Men's Denim Jeans | C13: Men's Fashion | D13: Jeans | E13: 1199 | F13: 699 | G13: 4.1 | H13: 540 | I13: FitDenim | J13: =LEFT(P13,1) -> 6 | K13: =MID(P13,3,1) -> 8 | L13: =E13*0.65 -> 779.35 | M13: =E13-F13 -> 500 | N13: =F13 - L13 -> -80.35 | O13: =(N13/F13) -> -0.11494993 | P13: 6-8 Days | Q13: In-Stock
... A31: MS030 | B31: Bathroom Anti-Slip Mat | C31: Home | D31: Bath | E31: 499 | F31: 229 | G31: 4.2 | H31: 450 | I31: HomeSafety | J31: =LEFT(P31,1) -> 3 | K31: =MID(P31,3,1) -> 5 | L31: =E31*0.65 -> 324.35 | M31: =E31-F31 -> 270 | N31: =F31 - L31 -> -95.35 | O31: =(N31/F31) -> -0.41637555 | P31: 3-5 Days | Q31: In-Stock

Sheet Customer
A1: Customer_ID2 | B1: Customer_name | C1: Gender | D1: City | E1: State | F1: Customer_Type
A2: C001 | B2: Rahul Sharma | C2: Male | D2: Delhi | E2: Delhi | F2: New
A3: C002 | B3: Nithya Jedeja | C3: Female | D3: Kochi | E3: Kerala | F3: Repeat
A4: C003 | B4: Athul Karma | C4: Male | D4: Bangalore | E4: Karnataka | F4: Repeat
A5: C004 | B5: Rohit V S | C5: Male | D5: Chennai | E5: Tamil Nadu | F5: Repeat
A6: C005 | B6: Amal Kumar | C6: Male | D6: Chennai | E6: Tamil Nadu | F6: Repeat
A7: C006 | B7: Arun S | C7: Male | D7: Bangalore | E7: Karnataka | F7: Repeat
A8: C007 | B8: Dhanya Vinod | C8: Female | D8: Bangalore | E8: Karnataka | F8: New
A9: C008 | B9: Sreesha J | C9: Female | D9: Hyderabad | E9: Telangana | F9: Repeat
A10: C009 | B10: Kamal Kumar | C10: Male | D10: Kochi | E10: Kerala | F10: New
A11: C010 | B11: Hirthya Dev | C11: Female | D11: Mumbai | E11: Maharashtra | F11: Repeat
A12: C011 | B12: Sharma K J | C12: Male | D12: Chennai | E12: Tamil Nadu | F12: Repeat
... A31: C030 | B31: Rohan Guptha | C31: Male | D31: Mumbai | E31: Maharashtra | F31: Repeat

Sheet Location_map
A1: City | B1: State
A2: Bangalore | B2: Karnataka
A3: Chennai | B3: Tamil Nadu
A4: Hyderabad | B4: Telangana
A5: Mumbai | B5: Maharashtra
A6: Delhi | B6: Delhi
A7: Kochi | B7: Kerala

Sheet Pivot_Revenue_BY_Category
A3: Row Labels | B3: Sum of Order_Revenue
A4: Accessories | B4: 4893
A5: Beauty | B5: 99
A6: Clothing | B6: 10106
A7: Footwear | B7: 6797
A8: Home | B8: 12421
A9: Jewellery | B9: 1972
A10: Kids | B10: 6110
A11: Men's Fashion | B11: 5888
A12: Grand Total | B12: 48286

Sheet Orders
A1: Order_ID | B1: Order_Date | C1: Customer_ID2 | D1: Product ID | E1: Quantity | F1: Payment_Mode | G1: Order_Status | H1: Unit_Selling_Price | I1: Order_Revenue | J1: Order_Cost | K1: Order_Profit
A2: O1001 | B2: 46079 | C2: C001 | D2: MS001 | E2: 5 | F2: UPI | G2: Delivered | H2: =_xlfn.XLOOKUP(D2, Product_clean!A:A, Product_clean!F:F) -> 349 | I2: =H2 * E2 -> 1745 | J2: =E2 * _xlfn.XLOOKUP(D2, Product_clean!A:A, Product_clean!L:L) -> 2271.75 | K2: =I2 - J2 -> -526.75
A3: O1002 | B3: 46074 | C3: C002 | D3: MS002 | E3: 4 | F3: CARD | G3: Delivered | H3: =_xlfn.XLOOKUP(D3, Product_clean!A:A, Product_clean!F:F) -> 549 | I3: =H3 * E3 -> 2196 | J3: =E3 * _xlfn.XLOOKUP(D3, Product_clean!A:A, Product_clean!L:L) -> 3117.4 | K3: =I3 - J3 -> -921.4
A4: O1003 | B4: 46028 | C4: C003 | D4: MS003 | E4: 3 | F4: CARD | G4: Delivered | H4: =_xlfn.XLOOKUP(D4, Product_clean!A:A, Product_clean!F:F) -> 399 | I4: =H4 * E4 -> 1197 | J4: =E4 * _xlfn.XLOOKUP(D4, Product_clean!A:A, Product_clean!L:L) -> 1558.05 | K4: =I4 - J4 -> -361.05
A5: O1004 | B5: 46043 | C5: C004 | D5: MS004 | E5: 1 | F5: COD | G5: Cancelled | H5: =_xlfn.XLOOKUP(D5, Product_clean!A:A, Product_clean!F:F) -> 179 | I5: =H5 * E5 -> 179 | J5: =E5 * _xlfn.XLOOKUP(D5, Product_clean!A:A, Product_clean!L:L) -> 194.35 | K5: =I5 - J5 -> -15.35
A6: O1005 | B6: 46077 | C6: C005 | D6: MS005 | E6: 1 | F6: UPI | G6: Cancelled | H6: =_xlfn.XLOOKUP(D6, Product_clean!A:A, Product_clean!F:F) -> 249 | I6: =H6 * E6 -> 249 | J6: =E6 * _xlfn.XLOOKUP(D6, Product_clean!A:A, Product_clean!L:L) -> 324.35 | K6: =I6 - J6 -> -75.35
A7: O1006 | B7: 46065 | C7: C006 | D7: MS006 | E7: 4 | F7: CARD | G7: Cancelled | H7: =_xlfn.XLOOKUP(D7, Product_clean!A:A, Product_clean!F:F) -> 499 | I7: =H7 * E7 -> 1996 | J7: =E7 * _xlfn.XLOOKUP(D7, Product_clean!A:A, Product_clean!L:L) -> 2337.4 | K7: =I7 - J7 -> -341.4
A8: O1007 | B8: 46030 | C8: C007 | D8: MS007 | E8: 3 | F8: CARD | G8: Delivered | H8: =_xlfn.XLOOKUP(D8, Product_clean!A:A, Product_clean!F:F) -> 259 | I8: =H8 * E8 -> 777 | J8: =E8 * _xlfn.XLOOKUP(D8, Product_clean!A:A, Product_clean!L:L) -> 973.05 | K8: =I8 - J8 -> -196.05
A9: O1008 | B9: 46056 | C9: C008 | D9: MS008 | E9: 2 | F9: CARD | G9: Delivered | H9: =_xlfn.XLOOKUP(D9, Product_clean!A:A, Product_clean!F:F) -> 699 | I9: =H9 * E9 -> 1398 | J9: =E9 * _xlfn.XLOOKUP(D9, Product_clean!A:A, Product_clean!L:L) -> 1688.7 | K9: =I9 - J9 -> -290.7
A10: O1009 | B10: 46062 | C10: C009 | D10: MS009 | E10: 2 | F10: UPI | G10: Delivered | H10: =_xlfn.XLOOKUP(D10, Product_clean!A:A, Product_clean!F:F) -> 799 | I10: =H10 * E10 -> 1598 | J10: =E10 * _xlfn.XLOOKUP(D10, Product_clean!A:A, Product_clean!L:L) -> 1948.7 | K10: =I10 - J10 -> -350.7
A11: O1010 | B11: 46041 | C11: C010 | D11: MS010 | E11: 7 | F11: UPI | G11: Delivered | H11: =_xlfn.XLOOKUP(D11, Product_clean!A:A, Product_clean!F:F) -> 189 | I11: =H11 * E11 -> 1323 | J11: =E11 * _xlfn.XLOOKUP(D11, Product_clean!A:A, Product_clean!L:L) -> 1815.45 | K11: =I11 - J11 -> -492.45
A12: O1011 | B12: 46037 | C12: C011 | D12: MS011 | E12: 8 | F12: CARD | G12: Cancelled | H12: =_xlfn.XLOOKUP(D12, Product_clean!A:A, Product_clean!F:F) -> 499 | I12: =H12 * E12 -> 3992 | J12: =E12 * _xlfn.XLOOKUP(D12, Product_clean!A:A, Product_clean!L:L) -> 5194.8 | K12: =I12 - J12 -> -1202.8
A13: O1012 | B13: 46051 | C13: C012 | D13: MS012 | E13: 4 | F13: CARD | G13: Delivered | H13: =_xlfn.XLOOKUP(D13, Product_clean!A:A, Product_clean!F:F) -> 699 | I13: =H13 * E13 -> 2796 | J13: =E13 * _xlfn.XLOOKUP(D13, Product_clean!A:A, Product_clean!L:L) -> 3117.4 | K13: =I13 - J13 -> -321.4
... A31: O1030 | B31: 46030 | C31: C030 | D31: MS030 | E31: 5 | F31: CARD | G31: Delivered | H31: =_xlfn.XLOOKUP(D31, Product_clean!A:A, Product_clean!F:F) -> 229 | I31: =H31 * E31 -> 1145 | J31: =E31 * _xlfn.XLOOKUP(D31, Product_clean!A:A, Product_clean!L:L) -> 1621.75 | K31: =I31 - J31 -> -476.75

Sheet Sheet10
A1: Data returned for Sum of Refund_Amount(PARTIAL) (First 1000 rows).
A3: tbl_Refund[Refund_ID] | B3: tbl_Refund[Order_ID] | C3: tbl_Refund[Product ID] | D3: tbl_Refund[Quantity] | E3: tbl_Refund[Order_Date] | F3: tbl_Refund[Refund_Date] | G3: tbl_Refund[Unit_Selling_Price] | H3: tbl_Refund[Order_Amount] | I3: tbl_Refund[Refund_Amount(PARTIAL)] | J3: tbl_Refund[Refund_Reason]
A4: R001 | B4: O1002 | C4: MS002 | D4: 4 | E4: 46074 | F4: 46078 | G4: 549 | H4: 2196 | I4: 1756.8 | J4: Late Delivery
A5: R002 | B5: O1004 | C5: MS004 | D5: 1 | E5: 46043 | F5: 46047 | G5: 179 | H5: 179 | I5: 143.2 | J5: Late Delivery
A6: R003 | B6: O1005 | C6: MS005 | D6: 1 | E6: 46077 | F6: 46078 | G6: 249 | H6: 249 | I6: 199.2 | J6: Order Cancelled by Customer
A7: R004 | B7: O1006 | C7: MS006 | D7: 4 | E7: 46065 | F7: 46070 | G7: 499 | H7: 1996 | I7: 1596.8 | J7: Wrong Item Delivered
A8: R005 | B8: O1011 | C8: MS011 | D8: 8 | E8: 46037 | F8: 46043 | G8: 499 | H8: 3992 | I8: 3193.6 | J8: Wrong Item Delivered
A9: R006 | B9: O1015 | C9: MS015 | D9: 4 | E9: 46056 | F9: 46058 | G9: 249 | H9: 996 | I9: 796.8 | J9: Damaged Product
A10: R007 | B10: O1019 | C10: MS019 | D10: 6 | E10: 46049 | F10: 46053 | G10: 149 | H10: 894 | I10: 715.2 | J10: Quality Issue
A11: R008 | B11: O1020 | C11: MS020 | D11: 7 | E11: 46078 | F11: 46084 | G11: 549 | H11: 3843 | I11: 3074.4 | J11: Damaged Product
A12: R009 | B12: O1021 | C12: MS021 | D12: 9 | E12: 46045 | F12: 46050 | G12: 349 | H12: 3141 | I12: 2512.8 | J12: Damaged Product
A13: R010 | B13: O1022 | C13: MS022 | D13: 1 | E13: 46081 | F13: 46088 | G13: 99 | H13: 99 | I13: 79.2 | J13: Wrong Item Delivered
A14: R011 | B14: O1024 | C14: MS024 | D14: 3 | E14: 46026 | F14: 46029 | G14: 299 | H14: 897 | I14: 717.6 | J14: Quality Issue
A15: R012 | B15: O1026 | C15: MS026 | D15: 4 | E15: 46023 | F15: 46027 | G15: 299 | H15: 1196 | I15: 956.8 | J15: Late Delivery
A16: R013 | B16: O1027 | C16: MS027 | D16: 3 | E16: 46043 | F16: 46047 | G16: 399 | H16: 1197 | I16: 957.6 | J16: Late Delivery

Sheet Ref_Amnt_By_Ref_Rsn_Pivot
A3: Row Labels | B3: Sum of Refund_Amount(PARTIAL)
A4: Damaged Product | B4: 6384
A5: Late Delivery | B5: 3814.4
A6: Order Cancelled by Customer | B6: 199.2
A7: Quality Issue | B7: 1432.8
A8: Wrong Item Delivered | B8: 4869.6
A9: Grand Total | B9: 16700

Sheet Refund
A1: Refund_ID | B1: Order_ID | C1: Product ID | D1: Quantity | E1: Order_Date | F1: Refund_Date | G1: Unit_Selling_Price | H1: Order_Amount | I1: Refund_Amount(PARTIAL) | J1: Refund_Reason
A2: R001 | B2: O1002 | C2: MS002 | D2: 4 | E2: 46074 | F2: =E2+ RANDBETWEEN(1,7) -> 46076 | G2: 549 | H2: =D2 * G2 -> 2196 | I2: =H2 * 0.8 -> 1756.8 | J2: Late Delivery
A3: R002 | B3: O1004 | C3: MS004 | D3: 1 | E3: 46043 | F3: =E3+ RANDBETWEEN(1,7) -> 46050 | G3: 179 | H3: =D3 * G3 -> 179 | I3: =H3 * 0.8 -> 143.2 | J3: Late Delivery
A4: R003 | B4: O1005 | C4: MS005 | D4: 1 | E4: 46077 | F4: =E4+ RANDBETWEEN(1,7) -> 46080 | G4: 249 | H4: =D4 * G4 -> 249 | I4: =H4 * 0.8 -> 199.2 | J4: Order Cancelled by Customer
A5: R004 | B5: O1006 | C5: MS006 | D5: 4 | E5: 46065 | F5: =E5+ RANDBETWEEN(1,7) -> 46072 | G5: 499 | H5: =D5 * G5 -> 1996 | I5: =H5 * 0.8 -> 1596.8 | J5: Wrong Item Delivered
A6: R005 | B6: O1011 | C6: MS011 | D6: 8 | E6: 46037 | F6: =E6+ RANDBETWEEN(1,7) -> 46043 | G6: 499 | H6: =D6 * G6 -> 3992 | I6: =H6 * 0.8 -> 3193.6 | J6: Wrong Item Delivered
A7: R006 | B7: O1015 | C7: MS015 | D7: 4 | E7: 46056 | F7: =E7+ RANDBETWEEN(1,7) -> 46063 | G7: 249 | H7: =D7 * G7 -> 996 | I7: =H7 * 0.8 -> 796.8 | J7: Damaged Product
A8: R007 | B8: O1019 | C8: MS019 | D8: 6 | E8: 46049 | F8: =E8+ RANDBETWEEN(1,7) -> 46054 | G8: 149 | H8: =D8 * G8 -> 894 | I8: =H8 * 0.8 -> 715.2 | J8: Quality Issue
A9: R008 | B9: O1020 | C9: MS020 | D9: 7 | E9: 46078 | F9: =E9+ RANDBETWEEN(1,7) -> 46080 | G9: 549 | H9: =D9 * G9 -> 3843 | I9: =H9 * 0.8 -> 3074.4 | J9: Damaged Product
A10: R009 | B10: O1021 | C10: MS021 | D10: 9 | E10: 46045 | F10: =E10+ RANDBETWEEN(1,7) -> 46046 | G10: 349 | H10: =D10 * G10 -> 3141 | I10: =H10 * 0.8 -> 2512.8 | J10: Damaged Product
A11: R010 | B11: O1022 | C11: MS022 | D11: 1 | E11: 46081 | F11: =E11+ RANDBETWEEN(1,7) -> 46085 | G11: 99 | H11: =D11 * G11 -> 99 | I11: =H11 * 0.8 -> 79.2 | J11: Wrong Item Delivered
A12: R011 | B12: O1024 | C12: MS024 | D12: 3 | E12: 46026 | F12: =E12+ RANDBETWEEN(1,7) -> 46029 | G12: 299 | H12: =D12 * G12 -> 897 | I12: =H12 * 0.8 -> 717.6 | J12: Quality Issue
A13: R012 | B13: O1026 | C13: MS026 | D13: 4 | E13: 46023 | F13: =E13+ RANDBETWEEN(1,7) -> 46026 | G13: 299 | H13: =D13 * G13 -> 1196 | I13: =H13 * 0.8 -> 956.8 | J13: Late Delivery
A14: R013 | B14: O1027 | C14: MS027 | D14: 3 | E14: 46043 | F14: =E14+ RANDBETWEEN(1,7) -> 46047 | G14: 399 | H14: =D14 * G14 -> 1197 | I14: =H14 * 0.8 -> 957.6 | J14: Late Delivery

Sheet Sheet11
A1: Data returned for Count of Order_ID (First 1000 rows).
A3: tbl_Delivery[Order_ID] | B3: tbl_Delivery[Ordered_Date] | C3: tbl_Delivery[Promised_Day] | D3: tbl_Delivery[Promised_Delivery_Date] | E3: tbl_Delivery[Actual_Day] | F3: tbl_Delivery[Actual_Delivery_date] | G3: tbl_Delivery[Delivery_Status]
A4: O1001 | B4: 46079 | C4: 3 | D4: 46082 | E4: 3 | F4: 46082 | G4: On-Time
A5: O1003 | B5: 46028 | C5: 4 | D5: 46032 | E5: 5 | F5: 46033 | G5: Late
A6: O1007 | B6: 46030 | C6: 2 | D6: 46032 | E6: 1 | F6: 46031 | G6: On-Time
A7: O1008 | B7: 46056 | C7: 6 | D7: 46062 | E7: 6 | F7: 46062 | G7: On-Time
A8: O1009 | B8: 46062 | C8: 7 | D8: 46069 | E8: 8 | F8: 46070 | G8: Late
A9: O1010 | B9: 46041 | C9: 4 | D9: 46045 | E9: 5 | F9: 46046 | G9: Late
A10: O1012 | B10: 46051 | C10: 5 | D10: 46056 | E10: 8 | F10: 46059 | G10: Late
A11: O1013 | B11: 46073 | C11: 3 | D11: 46076 | E11: 2 | F11: 46075 | G11: On-Time
A12: O1014 | B12: 46060 | C12: 7 | D12: 46067 | E12: 4 | F12: 46064 | G12: On-Time
A13: O1016 | B13: 46042 | C13: 2 | D13: 46044 | E13: 3 | F13: 46045 | G13: Late
A14: O1017 | B14: 46056 | C14: 4 | D14: 46060 | E14: 1 | F14: 46057 | G14: On-Time
A15: O1018 | B15: 46026 | C15: 4 | D15: 46030 | E15: 3 | F15: 46029 | G15: On-Time
... A20: O1030 | B20: 46030 | C20: 7 | D20: 46037 | E20: 4 | F20: 46034 | G20: On-Time

Sheet Pivot_On-Site VS Late
A3: Row Labels | B3: Count of Order_ID
A4: Late | B4: 6
A5: On-Time | B5: 11
A6: Grand Total | B6: 17

Sheet KPI_Summary
A1: KPI Name | B1: Values
A2: Total Revenue | B2: 48286
A3: Total Refund Amount | B3: 16700
A4: Refund Rate (%) | B4: =B3 / B2 -> 0.34585594
A5: Total Orders | B5: 17
A6: On-Time Delivery % | B6: =B10/B5 -> 0.64705882
B10: 11

Sheet Delivery
A1: Order_ID | B1: Ordered_Date | C1: Promised_Day | D1: Promised_Delivery_Date | E1: Actual_Day | F1: Actual_Delivery_date | G1: Delivery_Status
A2: O1001 | B2: =_xlfn.XLOOKUP(A2, Orders!A:A, Orders!B:B) -> 46079 | C2: 3 | D2: =B2+C2 -> 46082 | E2: 3 | F2: =B2+E2 -> 46082 | G2: =IF(F2 >D2,"Late","On-Time") -> On-Time
A3: O1003 | B3: =_xlfn.XLOOKUP(A3, Orders!A:A, Orders!B:B) -> 46028 | C3: 4 | D3: =B3+C3 -> 46032 | E3: 5 | F3: =B3+E3 -> 46033 | G3: =IF(F3 >D3,"Late","On-Time") -> Late
A4: O1007 | B4: =_xlfn.XLOOKUP(A4, Orders!A:A, Orders!B:B) -> 46030 | C4: 2 | D4: =B4+C4 -> 46032 | E4: 1 | F4: =B4+E4 -> 46031 | G4: =IF(F4 >D4,"Late","On-Time") -> On-Time
A5: O1008 | B5: =_xlfn.XLOOKUP(A5, Orders!A:A, Orders!B:B) -> 46056 | C5: 6 | D5: =B5+C5 -> 46062 | E5: 6 | F5: =B5+E5 -> 46062 | G5: =IF(F5 >D5,"Late","On-Time") -> On-Time
A6: O1009 | B6: =_xlfn.XLOOKUP(A6, Orders!A:A, Orders!B:B) -> 46062 | C6: 7 | D6: =B6+C6 -> 46069 | E6: 8 | F6: =B6+E6 -> 46070 | G6: =IF(F6 >D6,"Late","On-Time") -> Late
A7: O1010 | B7: =_xlfn.XLOOKUP(A7, Orders!A:A, Orders!B:B) -> 46041 | C7: 4 | D7: =B7+C7 -> 46045 | E7: 5 | F7: =B7+E7 -> 46046 | G7: =IF(F7 >D7,"Late","On-Time") -> Late
A8: O1012 | B8: =_xlfn.XLOOKUP(A8, Orders!A:A, Orders!B:B) -> 46051 | C8: 5 | D8: =B8+C8 -> 46056 | E8: 8 | F8: =B8+E8 -> 46059 | G8: =IF(F8 >D8,"Late","On-Time") -> Late
A9: O1013 | B9: =_xlfn.XLOOKUP(A9, Orders!A:A, Orders!B:B) -> 46073 | C9: 3 | D9: =B9+C9 -> 46076 | E9: 2 | F9: =B9+E9 -> 46075 | G9: =IF(F9 >D9,"Late","On-Time") -> On-Time
A10: O1014 | B10: =_xlfn.XLOOKUP(A10, Orders!A:A, Orders!B:B) -> 46060 | C10: 7 | D10: =B10+C10 -> 46067 | E10: 4 | F10: =B10+E10 -> 46064 | G10: =IF(F10 >D10,"Late","On-Time") -> On-Time
A11: O1016 | B11: =_xlfn.XLOOKUP(A11, Orders!A:A, Orders!B:B) -> 46042 | C11: 2 | D11: =B11+C11 -> 46044 | E11: 3 | F11: =B11+E11 -> 46045 | G11: =IF(F11 >D11,"Late","On-Time") -> Late
A12: O1017 | B12: =_xlfn.XLOOKUP(A12, Orders!A:A, Orders!B:B) -> 46056 | C12: 4 | D12: =B12+C12 -> 46060 | E12: 1 | F12: =B12+E12 -> 46057 | G12: =IF(F12 >D12,"Late","On-Time") -> On-Time
A13: O1018 | B13: =_xlfn.XLOOKUP(A13, Orders!A:A, Orders!B:B) -> 46026 | C13: 4 | D13: =B13+C13 -> 46030 | E13: 3 | F13: =B13+E13 -> 46029 | G13: =IF(F13 >D13,"Late","On-Time") -> On-Time
... A18: O1030 | B18: =_xlfn.XLOOKUP(A18, Orders!A:A, Orders!B:B) -> 46030 | C18: 7 | D18: =B18+C18 -> 46037 | E18: 4 | F18: =B18+E18 -> 46034 | G18: =IF(F18 >D18,"Late","On-Time") -> On-Time

Sheet Dashboard

Sheet Product
A1: Product ID | B1: Product Name | C1: Category | D1: Sub-Category | E1: Price | F1: Discount Price | G1: Ratings | H1: Reviews | I1: Seller Name | J1: Delivery Time | K1: Availability
A2: MS001 | B2: Womenâ€™s Rayon Printed Kurti | C2: Clothing | D2: Kurtis | E2: 699 | F2: 349 | G2: 4.2 | H2: 1250 | I2: TrendyHub | J2: 5â€“7 Days | K2: In-Stock
A3: MS002 | B3: Cotton Blend Saree | C3: Clothing | D3: Sarees | E3: 1199 | F3: 549 | G3: 4 | H3: 980 | I3: SareeVilla | J3: 6â€“8 Days | K3: In-Stock
A4: MS003 | B4: Menâ€™s Casual Slim Fit Shirt | C4: Menâ€™s Fashion | D4: Shirts | E4: 799 | F4: 399 | G4: 4.3 | H4: 650 | I4: UrbanWear | J4: 4â€“6 Days | K4: In-Stock
A5: MS004 | B5: Womenâ€™s Ankle Length Leggings | C5: Clothing | D5: Bottomwear | E5: 299 | F5: 179 | G5: 4.1 | H5: 1150 | I5: LeggingsWorld | J5: 5â€“7 Days | K5: In-Stock
A6: MS005 | B6: Stainless Steel Water Bottle 1L | C6: Home | D6: Kitchen | E6: 499 | F6: 249 | G6: 4.5 | H6: 820 | I6: HomeEssentials | J6: 3â€“5 Days | K6: In-Stock
A7: MS006 | B7: Printed Bedsheet with Pillow Covers | C7: Home | D7: Bedding | E7: 899 | F7: 499 | G7: 4.2 | H7: 720 | I7: DecorMagic | J7: 5â€“8 Days | K7: In-Stock
A8: MS007 | B8: Soft Baby Cotton Romper | C8: Kids | D8: Babywear | E8: 499 | F8: 259 | G8: 4.6 | H8: 500 | I8: LittleStars | J8: 4â€“6 Days | K8: In-Stock
A9: MS008 | B9: Womenâ€™s Faux Leather Handbag | C9: Accessories | D9: Bags | E9: 1299 | F9: 699 | G9: 4.3 | H9: 430 | I9: FashionBagHub | J9: 5â€“7 Days | K9: In-Stock
A10: MS009 | B10: Menâ€™s Running Sports Shoes | C10: Footwear | D10: Sports Shoes | E10: 1499 | F10: 799 | G10: 4.4 | H10: 780 | I10: Sportify | J10: 4â€“6 Days | K10: In-Stock
A11: MS010 | B11: Womenâ€™s Oxidised Silver Earrings | C11: Jewellery | D11: Earrings | E11: 399 | F11: 189 | G11: 4.5 | H11: 1050 | I11: JewelWorld | J11: 3â€“5 Days | K11: In-Stock
A12: MS011 | B12: Microfiber Double Bedsheet | C12: Home | D12: Bedding | E12: 999 | F12: 499 | G12: 4.2 | H12: 620 | I12: ComfortZone | J12: 5â€“7 Days | K12: In-Stock
A13: MS012 | B13: Menâ€™s Denim Jeans | C13: Menâ€™s Fashion | D13: Jeans | E13: 1199 | F13: 699 | G13: 4.1 | H13: 540 | I13: FitDenim | J13: 6â€“8 Days | K13: In-Stock
... A31: MS030 | B31: Bathroom Anti-Slip Mat | C31: Home | D31: Bath | E31: 499 | F31: 229 | G31: 4.2 | H31: 450 | I31: HomeSafety | J31: 3â€“5 Days | K31: In-Stock
B33: Ready to Grow Faster With Data?
B34: Get Custom Datasets That Boost Revenue, Optimize Pricing,
B35: and Give You an Unfair Competitor Advantage.
A37: Contact | B37: info@productdatascrape.com
A38: Website | B38: https://www.productdatascrape.com/
A39: WhatsApp | B39: +1 424 3777584
